verilog/memory/memory.v
module memory(input clk,input wr_rd,input [2:0]address, inout[7:0]data);

//wire clk;
//wire wr_rd;
//wire address;
reg [7:0] mem [7:0];
reg [7:0] out;
//reg [7:0]data;




assign data = (wr_rd)?out : 8'bZ;

always @(posedge clk)begin
  if(wr_rd == 0) begin
    mem[address] <= data;
  end else begin
    out <= mem[address];
  end
end

endmodule

verilog/memory/memory_tb.v
module memory_tb;
reg clk;
reg wr_rd;
reg [2:0]address;
wire [7:0] data;
reg [7:0] out;
memory dut(.clk (clk),.wr_rd (wr_rd),.address (address),.data (data));

initial
begin
  clk = 0;
  wr_rd = 0;
  address = 0;
end
always begin
  #5 clk = !clk;
end
initial  
begin
  $dumpfile ("memory.vcd"); 
  $dumpvars; 
end 

initial
begin
  wr_rd = 0;
  address = 3'b000;
  out = 8'b00000001;
  #10
  address = 3'b001;
  out = 8'b00000010;
  #10 
  address = 3'b010;
  out = 8'b00000011;
  #10
  wr_rd = 1;
  #10
  address = 3'b000;
  #10
  address = 3'b001;
  #10 
  address = 3'b010;
  $finish;
  
end
assign data = out;

endmodule

verilog/memory/memory.vcd
$date
	Thu Jun 29 00:53:44 2017
$end
$version
	Icarus Verilog
$end
$timescale
	1s
$end
$scope module memory_tb $end
$var wire 8 ! data [7:0] $end
$var reg 3 " address [2:0] $end
$var reg 1 # clk $end
$var reg 8 $ out [7:0] $end
$var reg 1 % wr_rd $end
$scope module dut $end
$var wire 3 & address [2:0] $end
$var wire 1 # clk $end
$var wire 8 ' data [7:0] $end
$var wire 1 % wr_rd $end
$var reg 8 ( out [7:0] $end
$upscope $end
$upscope $end
$enddefinitions $end
#0
$dumpvars
bx (
b1 '
b0 &
0%
b1 $
0#
b0 "
b1 !
$end
#5
1#
#10
0#
b10 !
b10 '
b10 $
b1 "
b1 &
#15
1#
#20
0#
b11 !
b11 '
b11 $
b10 "
b10 &
#25
1#
#30
bx !
bx '
0#
1%
#35
b11 !
b11 '
b11 (
1#
#40
0#
b0 "
b0 &
#45
b0x1 !
b0x1 '
b1 (
1#
#50
0#
b1 "
b1 &
#55
b1x !
b1x '
b10 (
1#
#60
0#
b10 "
b10 &
